README.txt
bootstrap.py
buildout.cfg
setup.py
docs/HISTORY.txt
src/munin/__init__.py
src/munin.varnish.egg-info/PKG-INFO
src/munin.varnish.egg-info/SOURCES.txt
src/munin.varnish.egg-info/dependency_links.txt
src/munin.varnish.egg-info/entry_points.txt
src/munin.varnish.egg-info/namespace_packages.txt
src/munin.varnish.egg-info/not-zip-safe
src/munin.varnish.egg-info/requires.txt
src/munin.varnish.egg-info/top_level.txt
src/munin/varnish/__init__.py
src/munin/varnish/varnish_