Metadata-Version: 1.0
Name: munin.varnish
Version: 1.0a3
Summary: Munin plugins for Varnish.
Home-page: http://pypi.python.org/pypi/munin.varnish
Author: Michael Dunstan
Author-email: michael@elyt.com
License: GPL
Keywords: munin monitoring
Platform: Any
Classifier: Development Status :: 3 - Alpha
Classifier: Framework :: Buildout
Classifier: Intended Audience :: Developers
Classifier: Topic :: Software Development :: Build Tools
Classifier: Topic :: System :: Networking :: Monitoring
Classifier: License :: OSI Approved :: GNU General Public License (GPL)
